{
  "Id": "dd31cdd2-f651-4d47-9755-937a44892c68",
  "Type": 2,
  "Caption": "SaveMenuPermission",
  "Name": "SaveMenuPermission",
  "Transitions": [
    {
      "Id": "1023b511-ef7d-43bc-bf7f-b9829494e5c4",
      "Name": "SaveMenuPermission",
      "ActionPoint": {
        "TypeName": "Action",
        "ScenarioId": "e2586d23-5056-4a5f-8b34-54327ce97830"
      }
    }
  ],
  "SettingsType": "Custom",
  "ParentId": "bd4bfcb7-daf8-4e52-b317-a2b9ed6b0480",
  "__ConfigId": "systemconfig",
  "__DocumentId": "processmetadata"
}
